{
  "version": "7",
  "dialect": "mysql",
  "entries": [
    {
      "idx": 0,
      "version": "5",
      "when": 1751649409405,
      "tag": "0000_fluffy_northstar",
      "breakpoints": true
    },
    {
      "idx": 1,
      "version": "5",
      "when": 1751649511074,
      "tag": "0001_adorable_kat_farrell",
      "breakpoints": true
    },
    {
      "idx": 2,
      "version": "5",
      "when": 1751735211910,
      "tag": "0002_vengeful_the_executioner",
      "breakpoints": true
    },
    {
      "idx": 3,
      "version": "5",
      "when": 1751735278958,
      "tag": "0003_salty_bucky",
      "breakpoints": true
    }
  ]
}